Metadata-Version: 2.1
Name: cached
Version: 2019.3.22
Summary: cached(function) - cache function
Home-page: https://github.com/looking-for-a-job/cached.py
License: UNKNOWN
Keywords: cached cache function
Platform: UNKNOWN
Classifier: License :: Public Domain
Classifier: Operating System :: OS Independent
Classifier: Programming Language :: Python
Classifier: Programming Language :: Python :: 2
Classifier: Programming Language :: Python :: 2.7
Classifier: Programming Language :: Python :: 3
Classifier: Programming Language :: Python :: 3.4
Classifier: Programming Language :: Python :: 3.5
Classifier: Programming Language :: Python :: 3.6
Classifier: Programming Language :: Python :: 3.7
Classifier: Topic :: Software Development
Requires-Dist: decorator
Requires-Dist: public
Requires-Dist: setuptools
